examples/__init__.py
seaqube/__init__.py
seaqube/download.py
seaqube/package_config.py
seaqube/augmentation/__init__.py
seaqube/augmentation/base.py
seaqube/augmentation/char/__init__.py
seaqube/augmentation/char/qwerty.py
seaqube/augmentation/corpus/__init__.py
seaqube/augmentation/corpus/unigram.py
seaqube/augmentation/misc/__init__.py
seaqube/augmentation/misc/embedding_model_wrapper.py
seaqube/augmentation/misc/model_loader.py
seaqube/augmentation/misc/qwerty_lookup_table.py
seaqube/augmentation/reduction/__init__.py
seaqube/augmentation/reduction/_reduction.py
seaqube/augmentation/reduction/unique_corpus.py
seaqube/augmentation/word/__init__.py
seaqube/augmentation/word/active2passive.py
seaqube/augmentation/word/eda.py
seaqube/augmentation/word/embedding.py
seaqube/augmentation/word/translation.py
seaqube/benchmark/__init__.py
seaqube/benchmark/_benchmark.py
seaqube/benchmark/corpus4ir.py
seaqube/benchmark/semantic_wordnet.py
seaqube/benchmark/wordanalogy.py
seaqube/benchmark/wordoutliers.py
seaqube/benchmark/wordsimilarity.py
seaqube/benchmark/benchmark_datasets/README.md
seaqube/benchmark/benchmark_datasets/dataset_map.json
seaqube/benchmark/benchmark_datasets/outlier-detection/monolingual/en/8-8-8.csv
seaqube/benchmark/benchmark_datasets/outlier-detection/monolingual/en/wikisem500.csv
seaqube/benchmark/benchmark_datasets/semantic-relation/monolingual/en/bless.csv
seaqube/benchmark/benchmark_datasets/semantic-relation/monolingual/en/sn.csv
seaqube/benchmark/benchmark_datasets/word-analogy/monolingual/en/google-analogies.csv
seaqube/benchmark/benchmark_datasets/word-analogy/monolingual/en/jair.csv
seaqube/benchmark/benchmark_datasets/word-analogy/monolingual/en/msr.csv
seaqube/benchmark/benchmark_datasets/word-analogy/monolingual/en/sat.csv
seaqube/benchmark/benchmark_datasets/word-analogy/monolingual/en/semeval.csv
seaqube/benchmark/benchmark_datasets/word-categorization/monolingual/en/ap.csv
seaqube-0.1.11.dist-info/LICENSE
seaqube-0.1.11.dist-info/METADATA
seaqube-0.1.11.dist-info/WHEEL
seaqube-0.1.11.dist-info/top_level.txt
seaqube-0.1.11.dist-info/RECORD
