Metadata-Version: 2.1
Name: seaqube
Version: 0.1.11
Summary: Semantic Quality Benchmark for Word Embeddings, i.e. Natural Language Models in Python. The shortname is `SeaQuBe` or `seaqube`. Simple call it '| ˈsi: kjuːb |'
Home-page: https://github.com/bees4ever/seaqube
Author: Benjamin Manns
Author-email: benjamin.manns@mni.thm.de
License: UNKNOWN
Platform: UNKNOWN
Classifier: Programming Language :: Python :: 3.0
Classifier: License :: OSI Approved :: MIT License
Classifier: Operating System :: OS Independent
Requires-Python: >=3
Requires-Dist: dill
Requires-Dist: gensim
Requires-Dist: googletrans (==3.0.0)
Requires-Dist: nltk (==3.5)
Requires-Dist: numpy
Requires-Dist: pandas
Requires-Dist: pathos (==0.2.6)
Requires-Dist: progressbar2
Requires-Dist: pyinflect (==0.5.1)
Requires-Dist: schedule
Requires-Dist: scikit-learn
Requires-Dist: scipy
Requires-Dist: sklearn
Requires-Dist: spacy (==2.3.2)
Requires-Dist: chainer
Requires-Dist: tokenizers (==0.9.3)
Requires-Dist: transformers (==3.5.1)
Requires-Dist: tensorboardX
Requires-Dist: tqdm
